MANIFEST.in
setup.py
edge_testing_framework/__init__.py
edge_testing_framework/autotest.py
edge_testing_framework/config.py
edge_testing_framework/data.py
edge_testing_framework/database.py
edge_testing_framework/globals.py
edge_testing_framework/junit.py
edge_testing_framework/log.py
edge_testing_framework/page_variables.py
edge_testing_framework/parse.py
edge_testing_framework/report.py
edge_testing_framework/testcase.py
edge_testing_framework/testsuite.py
edge_testing_framework/utility.py
edge_testing_framework.egg-info/PKG-INFO
edge_testing_framework.egg-info/SOURCES.txt
edge_testing_framework.egg-info/dependency_links.txt
edge_testing_framework.egg-info/requires.txt
edge_testing_framework.egg-info/top_level.txt
edge_testing_framework/client/__init__.py
edge_testing_framework/keywords/__init__.py
edge_testing_framework/keywords/common.py
edge_testing_framework/keywords/ctypes_k.py
edge_testing_framework/keywords/files.py
edge_testing_framework/keywords/http.py
edge_testing_framework/keywords/modbus_k.py
edge_testing_framework/keywords/mqtt.py
edge_testing_framework/keywords/run_common_obj_per.py
edge_testing_framework/keywords/run_ctypes_k_obj_per.py
edge_testing_framework/lib/__init__.py
edge_testing_framework/lib/c.py
edge_testing_framework/lib/func.py
edge_testing_framework/lib/http_handle.py
edge_testing_framework/lib/injson_ok.py
edge_testing_framework/lib/obj_persistence.py
edge_testing_framework/lib/struct.py
edge_testing_framework/pytransform/__init__.py
edge_testing_framework/pytransform/_pytransform.dll
edge_testing_framework/servers/__init__.py
edge_testing_framework/servers/common.py
edge_testing_framework/servers/ctypes_client.py
edge_testing_framework/servers/modbus_client.py
edge_testing_framework/servers/mqtt_client.py
edge_testing_framework/servers/teardown.py