Metadata-Version: 2.1
Name: edge-testing-framework
Version: 0.1.7
Summary: 关键字驱动测试框架：支持c++接口文件dll/so的加载测试、http、mqtt、db、modbus等
Home-page: https://github.com/
Author: liyubin
Author-email: 1399393088@qq.com
License: MIT Licence
Keywords: pip,edge_testing_framework,featureextraction
Platform: any
